miyadaiku/themes/fontawesome/__init__.py
miyadaiku/themes/fontawesome/config.yml
miyadaiku/themes/fontawesome/externals/css/all.css
miyadaiku/themes/fontawesome/externals/css/brands.css
miyadaiku/themes/fontawesome/externals/css/font-awesome.css
miyadaiku/themes/fontawesome/externals/css/font-awesome.min.css
miyadaiku/themes/fontawesome/externals/css/fontawesome.css
miyadaiku/themes/fontawesome/externals/css/regular.css
miyadaiku/themes/fontawesome/externals/css/solid.css
miyadaiku/themes/fontawesome/externals/css/svg-with-js.css
miyadaiku/themes/fontawesome/externals/css/v4-shims.css
miyadaiku/themes/fontawesome/externals/css/v4-shims.min.css
miyadaiku/themes/fontawesome/files/static/fontawesome/fonts/FontAwesome.otf
miyadaiku/themes/fontawesome/files/static/fontawesome/fonts/fontawesome-webfont.eot
miyadaiku/themes/fontawesome/files/static/fontawesome/fonts/fontawesome-webfont.svg
miyadaiku/themes/fontawesome/files/static/fontawesome/fonts/fontawesome-webfont.ttf
miyadaiku/themes/fontawesome/files/static/fontawesome/fonts/fontawesome-webfont.woff
miyadaiku/themes/fontawesome/files/static/fontawesome/fonts/fontawesome-webfont.woff2
miyadaiku/themes/fontawesome/templates/macros.html
miyadaiku.themes.fontawesome-0.0.6.dist-info/DESCRIPTION.rst
miyadaiku.themes.fontawesome-0.0.6.dist-info/METADATA
miyadaiku.themes.fontawesome-0.0.6.dist-info/RECORD
miyadaiku.themes.fontawesome-0.0.6.dist-info/WHEEL
miyadaiku.themes.fontawesome-0.0.6.dist-info/metadata.json
miyadaiku.themes.fontawesome-0.0.6.dist-info/top_level.txt
